{"textures":{"0":"modelengine:entity/texture"},"elements":[{"from":[1.5,3.0,1.5],"to":[11.5,8.0,14.5],"faces":{"east":{"uv":[1.25,0.4375,2.0625,0.75],"tintindex":0,"rotation":0,"texture":"#0"},"south":{"uv":[4.0,3.0625,4.625,3.375],"tintindex":0,"rotation":0,"texture":"#0"},"north":{"uv":[4.0,0.0,4.625,0.3125],"tintindex":0,"rotation":0,"texture":"#0"},"west":{"uv":[2.9375,2.375,3.75,2.6875],"tintindex":0,"rotation":0,"texture":"#0"},"up":{"uv":[0.625,0.8125,0.0,0.0],"tintindex":0,"rotation":0,"texture":"#0"},"down":{"uv":[1.25,0.0,0.625,0.8125],"tintindex":0,"rotation":0,"texture":"#0"}}}],"display":{"gui":{"rotation":[30,225,0]}}}