{"elements":[{"from":[7.245714,7.9049892,7.4905896],"to":[8.754286,8.556417,8.604876],"rotation":{"angle":0.0,"axis":"y","origin":[8.0,11.144989,9.787733]},"faces":{"east":{"uv":[4.0,4.0,5.0,5.0],"rotation":270,"texture":"#0","tintindex":0},"south":{"uv":[4.0,4.0,5.0,5.0],"rotation":0,"texture":"#0","tintindex":0},"north":{"uv":[4.0,4.0,5.0,5.0],"rotation":180,"texture":"#0","tintindex":0},"west":{"uv":[4.0,4.0,5.0,5.0],"rotation":90,"texture":"#0","tintindex":0},"up":{"uv":[4.0,4.0,5.0,5.0],"rotation":180,"texture":"#0","tintindex":0},"down":{"uv":[4.0,4.0,5.0,5.0],"rotation":0,"texture":"#0","tintindex":0}}},{"from":[7.245714,7.8969812,6.010331],"to":[8.754286,8.54841,7.62176],"rotation":{"angle":-22.5,"axis":"x","origin":[8.0,8.222695,7.5360456]},"faces":{"east":{"uv":[4.0,4.0,5.0,5.0],"rotation":270,"texture":"#0","tintindex":0},"south":{"uv":[4.0,4.0,5.0,5.0],"rotation":0,"texture":"#0","tintindex":0},"north":{"uv":[4.0,4.0,5.0,5.0],"rotation":180,"texture":"#0","tintindex":0},"west":{"uv":[4.0,4.0,5.0,5.0],"rotation":90,"texture":"#0","tintindex":0},"up":{"uv":[4.0,4.0,5.0,5.0],"rotation":180,"texture":"#0","tintindex":0},"down":{"uv":[4.0,4.0,5.0,5.0],"rotation":0,"texture":"#0","tintindex":0}}},{"from":[7.245714,7.2883224,5.8303947],"to":[8.754286,7.9397507,8.864681],"rotation":{"angle":0.0,"axis":"y","origin":[8.0,10.528322,7.9561095]},"faces":{"east":{"uv":[4.0,4.0,5.0,5.0],"rotation":270,"texture":"#0","tintindex":0},"south":{"uv":[4.0,4.0,5.0,5.0],"rotation":0,"texture":"#0","tintindex":0},"north":{"uv":[4.0,4.0,5.0,5.0],"rotation":180,"texture":"#0","tintindex":0},"west":{"uv":[4.0,4.0,5.0,5.0],"rotation":90,"texture":"#0","tintindex":0},"up":{"uv":[4.0,4.0,5.0,5.0],"rotation":180,"texture":"#0","tintindex":0},"down":{"uv":[4.0,4.0,5.0,5.0],"rotation":0,"texture":"#0","tintindex":0}}},{"from":[7.245714,7.7964764,8.145528],"to":[8.754286,8.465048,8.796956],"rotation":{"angle":-22.5,"axis":"x","origin":[8.0,8.027905,8.471242]},"faces":{"east":{"uv":[4.0,4.0,3.0,5.0],"rotation":0,"texture":"#0","tintindex":0},"south":{"uv":[4.0,4.0,5.0,5.0],"rotation":180,"texture":"#0","tintindex":0},"north":{"uv":[4.0,4.0,5.0,5.0],"rotation":180,"texture":"#0","tintindex":0},"west":{"uv":[4.0,4.0,3.0,5.0],"rotation":0,"texture":"#0","tintindex":0},"up":{"uv":[4.0,4.0,5.0,5.0],"rotation":0,"texture":"#0","tintindex":0},"down":{"uv":[4.0,4.0,5.0,5.0],"rotation":0,"texture":"#0","tintindex":0}}},{"from":[7.5885715,7.9740367,7.544681],"to":[8.411428,8.968323,8.538967],"rotation":{"angle":0.0,"axis":"y","origin":[8.0,11.556894,8.127538]},"faces":{"east":{"uv":[4.0,4.0,5.0,5.0],"rotation":270,"texture":"#0","tintindex":0},"south":{"uv":[4.0,4.0,5.0,5.0],"rotation":0,"texture":"#0","tintindex":0},"north":{"uv":[4.0,4.0,5.0,5.0],"rotation":180,"texture":"#0","tintindex":0},"west":{"uv":[4.0,4.0,5.0,5.0],"rotation":90,"texture":"#0","tintindex":0},"up":{"uv":[4.0,4.0,5.0,5.0],"rotation":180,"texture":"#0","tintindex":0},"down":{"uv":[4.0,4.0,5.0,5.0],"rotation":0,"texture":"#0","tintindex":0}}}],"textures":{"0":"modelengine:entity/bone_block_side"},"display":{"head":{"translation":[0.0,-6.4,0.0],"scale":[4.0,4.0,4.0]}}}