{"textures":{"0":"modelengine:entity/sharkman"},"elements":[{"name":"cube","from":[6.209754,10.629193,2.6735556],"to":[9.809754,13.329193,4.4735556],"rotation":{"angle":22.5,"axis":"x","origin":[0.80975413,-1.9708071,-3.6264448]},"faces":{"down":{"uv":[13.0,1.0,14.0,2.0],"rotation":0,"texture":"#0","tintindex":0},"east":{"uv":[13.0,1.0,14.0,2.0],"rotation":0,"texture":"#0","tintindex":0},"north":{"uv":[13.0,1.0,14.0,2.0],"rotation":0,"texture":"#0","tintindex":0},"south":{"uv":[13.0,1.0,14.0,2.0],"rotation":0,"texture":"#0","tintindex":0},"up":{"uv":[13.0,1.0,14.0,2.0],"rotation":0,"texture":"#0","tintindex":0},"west":{"uv":[13.0,1.0,14.0,2.0],"rotation":0,"texture":"#0","tintindex":0}}},{"name":"cube","from":[6.4347544,12.4291935,-1.8264446],"to":[9.584755,14.6791935,-0.026444674],"rotation":{"angle":45.0,"axis":"x","origin":[0.80975413,-1.9708071,-3.6264448]},"faces":{"down":{"uv":[13.0,1.0,14.0,2.0],"rotation":0,"texture":"#0","tintindex":0},"east":{"uv":[13.0,1.0,14.0,2.0],"rotation":0,"texture":"#0","tintindex":0},"north":{"uv":[13.0,1.0,14.0,2.0],"rotation":0,"texture":"#0","tintindex":0},"south":{"uv":[13.0,1.0,14.0,2.0],"rotation":0,"texture":"#0","tintindex":0},"up":{"uv":[13.0,1.0,14.0,2.0],"rotation":0,"texture":"#0","tintindex":0},"west":{"uv":[13.0,1.0,14.0,2.0],"rotation":0,"texture":"#0","tintindex":0}}},{"name":"cube","from":[6.4347544,1.3041853,12.595933],"to":[9.584755,3.1041853,13.045933],"rotation":{"angle":-22.5,"axis":"x","origin":[0.584754,-2.295815,-3.6040668]},"faces":{"down":{"uv":[13.0,1.0,14.0,2.0],"rotation":0,"texture":"#0","tintindex":0},"east":{"uv":[13.0,1.0,14.0,2.0],"rotation":270,"texture":"#0","tintindex":0},"north":{"uv":[13.0,1.0,14.0,2.0],"rotation":180,"texture":"#0","tintindex":0},"south":{"uv":[13.0,1.0,14.0,2.0],"rotation":0,"texture":"#0","tintindex":0},"up":{"uv":[13.0,1.0,14.0,2.0],"rotation":180,"texture":"#0","tintindex":0},"west":{"uv":[13.0,1.0,14.0,2.0],"rotation":90,"texture":"#0","tintindex":0}}},{"name":"cube","from":[6.6597543,12.4291935,-0.026444674],"to":[9.359755,14.229194,1.7735555],"rotation":{"angle":45.0,"axis":"x","origin":[0.80975413,-1.9708071,-3.6264448]},"faces":{"down":{"uv":[13.0,1.0,14.0,2.0],"rotation":0,"texture":"#0","tintindex":0},"east":{"uv":[13.0,1.0,14.0,2.0],"rotation":0,"texture":"#0","tintindex":0},"north":{"uv":[13.0,1.0,14.0,2.0],"rotation":0,"texture":"#0","tintindex":0},"south":{"uv":[13.0,1.0,14.0,2.0],"rotation":0,"texture":"#0","tintindex":0},"up":{"uv":[13.0,1.0,14.0,2.0],"rotation":0,"texture":"#0","tintindex":0},"west":{"uv":[13.0,1.0,14.0,2.0],"rotation":0,"texture":"#0","tintindex":0}}},{"name":"cube","from":[6.6597543,-1.157332,12.990297],"to":[9.359755,0.642668,13.440297],"rotation":{"angle":-22.5,"axis":"x","origin":[0.584754,-2.9573317,-4.5597034]},"faces":{"down":{"uv":[13.0,1.0,14.0,2.0],"rotation":0,"texture":"#0","tintindex":0},"east":{"uv":[13.0,1.0,14.0,2.0],"rotation":270,"texture":"#0","tintindex":0},"north":{"uv":[13.0,1.0,14.0,2.0],"rotation":180,"texture":"#0","tintindex":0},"south":{"uv":[13.0,1.0,14.0,2.0],"rotation":0,"texture":"#0","tintindex":0},"up":{"uv":[13.0,1.0,14.0,2.0],"rotation":180,"texture":"#0","tintindex":0},"west":{"uv":[13.0,1.0,14.0,2.0],"rotation":90,"texture":"#0","tintindex":0}}},{"name":"cube","from":[6.884754,-2.4208074,11.673556],"to":[9.134754,-0.6208072,13.248556],"rotation":{"angle":-22.5,"axis":"x","origin":[0.80975413,-1.9708071,-3.6264448]},"faces":{"down":{"uv":[13.0,1.0,14.0,2.0],"rotation":0,"texture":"#0","tintindex":0},"east":{"uv":[13.0,1.0,14.0,2.0],"rotation":270,"texture":"#0","tintindex":0},"north":{"uv":[13.0,1.0,14.0,2.0],"rotation":180,"texture":"#0","tintindex":0},"south":{"uv":[13.0,1.0,14.0,2.0],"rotation":0,"texture":"#0","tintindex":0},"up":{"uv":[13.0,1.0,14.0,2.0],"rotation":180,"texture":"#0","tintindex":0},"west":{"uv":[13.0,1.0,14.0,2.0],"rotation":90,"texture":"#0","tintindex":0}}},{"name":"cube","from":[6.884754,3.8659458,10.972062],"to":[9.134754,5.665946,11.647062],"rotation":{"angle":0.0,"axis":"x","origin":[0.584754,-1.9840536,-6.1279383]},"faces":{"down":{"uv":[13.0,1.0,14.0,2.0],"rotation":0,"texture":"#0","tintindex":0},"east":{"uv":[13.0,1.0,14.0,2.0],"rotation":270,"texture":"#0","tintindex":0},"north":{"uv":[13.0,1.0,14.0,2.0],"rotation":180,"texture":"#0","tintindex":0},"south":{"uv":[13.0,1.0,14.0,2.0],"rotation":0,"texture":"#0","tintindex":0},"up":{"uv":[13.0,1.0,14.0,2.0],"rotation":180,"texture":"#0","tintindex":0},"west":{"uv":[13.0,1.0,14.0,2.0],"rotation":90,"texture":"#0","tintindex":0}}},{"name":"cube","from":[7.5597544,7.479193,8.973556],"to":[8.459755,8.379193,11.673556],"rotation":{"angle":0.0,"axis":"x","origin":[0.80975413,-1.9708071,-3.6264448]},"faces":{"down":{"uv":[13.0,1.0,14.0,2.0],"rotation":0,"texture":"#0","tintindex":0},"east":{"uv":[13.0,1.0,14.0,2.0],"rotation":0,"texture":"#0","tintindex":0},"north":{"uv":[13.0,1.0,14.0,2.0],"rotation":0,"texture":"#0","tintindex":0},"south":{"uv":[13.0,1.0,14.0,2.0],"rotation":0,"texture":"#0","tintindex":0},"up":{"uv":[13.0,1.0,14.0,2.0],"rotation":0,"texture":"#0","tintindex":0},"west":{"uv":[13.0,1.0,14.0,2.0],"rotation":0,"texture":"#0","tintindex":0}}},{"name":"cube","from":[7.5597544,5.679193,9.873556],"to":[8.459755,7.479193,11.673556],"rotation":{"angle":0.0,"axis":"x","origin":[0.80975413,-1.9708071,-3.6264448]},"faces":{"down":{"uv":[13.0,1.0,14.0,2.0],"rotation":0,"texture":"#0","tintindex":0},"east":{"uv":[13.0,1.0,14.0,2.0],"rotation":0,"texture":"#0","tintindex":0},"north":{"uv":[13.0,1.0,14.0,2.0],"rotation":0,"texture":"#0","tintindex":0},"south":{"uv":[13.0,1.0,14.0,2.0],"rotation":0,"texture":"#0","tintindex":0},"up":{"uv":[13.0,1.0,14.0,2.0],"rotation":0,"texture":"#0","tintindex":0},"west":{"uv":[13.0,1.0,14.0,2.0],"rotation":0,"texture":"#0","tintindex":0}}},{"name":"cube","from":[7.5597544,4.329193,10.773556],"to":[8.459755,5.2291927,16.173557],"rotation":{"angle":0.0,"axis":"x","origin":[0.80975413,-1.9708071,-3.6264448]},"faces":{"down":{"uv":[13.0,1.0,14.0,2.0],"rotation":0,"texture":"#0","tintindex":0},"east":{"uv":[13.0,1.0,14.0,2.0],"rotation":270,"texture":"#0","tintindex":0},"north":{"uv":[13.0,1.0,14.0,2.0],"rotation":180,"texture":"#0","tintindex":0},"south":{"uv":[13.0,1.0,14.0,2.0],"rotation":0,"texture":"#0","tintindex":0},"up":{"uv":[13.0,1.0,14.0,2.0],"rotation":180,"texture":"#0","tintindex":0},"west":{"uv":[13.0,1.0,14.0,2.0],"rotation":90,"texture":"#0","tintindex":0}}},{"name":"cube","from":[7.5579543,3.429193,10.773556],"to":[8.461555,4.329193,15.273556],"rotation":{"angle":0.0,"axis":"x","origin":[0.80975413,-1.9708071,-3.6264448]},"faces":{"down":{"uv":[13.0,1.0,14.0,2.0],"rotation":0,"texture":"#0","tintindex":0},"east":{"uv":[13.0,1.0,14.0,2.0],"rotation":270,"texture":"#0","tintindex":0},"north":{"uv":[13.0,1.0,14.0,2.0],"rotation":180,"texture":"#0","tintindex":0},"south":{"uv":[13.0,1.0,14.0,2.0],"rotation":0,"texture":"#0","tintindex":0},"up":{"uv":[13.0,1.0,14.0,2.0],"rotation":180,"texture":"#0","tintindex":0},"west":{"uv":[13.0,1.0,14.0,2.0],"rotation":90,"texture":"#0","tintindex":0}}},{"name":"cube","from":[7.5597544,7.029193,8.073556],"to":[8.459755,9.729193,8.973556],"rotation":{"angle":22.5,"axis":"x","origin":[0.80975413,-1.9708071,-3.6264448]},"faces":{"down":{"uv":[13.0,1.0,14.0,2.0],"rotation":0,"texture":"#0","tintindex":0},"east":{"uv":[13.0,1.0,14.0,2.0],"rotation":180,"texture":"#0","tintindex":0},"north":{"uv":[13.0,1.0,14.0,2.0],"rotation":180,"texture":"#0","tintindex":0},"south":{"uv":[13.0,1.0,14.0,2.0],"rotation":180,"texture":"#0","tintindex":0},"up":{"uv":[13.0,1.0,14.0,2.0],"rotation":0,"texture":"#0","tintindex":0},"west":{"uv":[13.0,1.0,14.0,2.0],"rotation":180,"texture":"#0","tintindex":0}}},{"name":"cube","from":[7.5597544,15.860727,4.6111774],"to":[8.459755,17.143227,5.511178],"rotation":{"angle":45.0,"axis":"x","origin":[0.80975413,-2.1392736,-4.6138225]},"faces":{"down":{"uv":[13.0,1.0,14.0,2.0],"rotation":0,"texture":"#0","tintindex":0},"east":{"uv":[13.0,1.0,14.0,2.0],"rotation":180,"texture":"#0","tintindex":0},"north":{"uv":[13.0,1.0,14.0,2.0],"rotation":180,"texture":"#0","tintindex":0},"south":{"uv":[13.0,1.0,14.0,2.0],"rotation":180,"texture":"#0","tintindex":0},"up":{"uv":[13.0,1.0,14.0,2.0],"rotation":0,"texture":"#0","tintindex":0},"west":{"uv":[13.0,1.0,14.0,2.0],"rotation":180,"texture":"#0","tintindex":0}}},{"name":"cube","from":[7.5579543,-4.569273,10.461178],"to":[8.457954,-3.669273,11.698678],"rotation":{"angle":-22.5,"axis":"x","origin":[0.80975413,-2.1392736,-3.7138228]},"faces":{"down":{"uv":[13.0,1.0,14.0,2.0],"rotation":180,"texture":"#0","tintindex":0},"east":{"uv":[13.0,1.0,14.0,2.0],"rotation":90,"texture":"#0","tintindex":0},"north":{"uv":[13.0,1.0,14.0,2.0],"rotation":180,"texture":"#0","tintindex":0},"south":{"uv":[13.0,1.0,14.0,2.0],"rotation":0,"texture":"#0","tintindex":0},"up":{"uv":[13.0,1.0,14.0,2.0],"rotation":0,"texture":"#0","tintindex":0},"west":{"uv":[13.0,1.0,14.0,2.0],"rotation":270,"texture":"#0","tintindex":0}}},{"name":"cube","from":[7.5597544,6.1516924,7.1735563],"to":[8.459755,9.729193,8.073556],"rotation":{"angle":22.5,"axis":"x","origin":[0.80975413,-1.9708071,-3.6264448]},"faces":{"down":{"uv":[13.0,1.0,14.0,2.0],"rotation":0,"texture":"#0","tintindex":0},"east":{"uv":[13.0,1.0,14.0,2.0],"rotation":180,"texture":"#0","tintindex":0},"north":{"uv":[13.0,1.0,14.0,2.0],"rotation":180,"texture":"#0","tintindex":0},"south":{"uv":[13.0,1.0,14.0,2.0],"rotation":180,"texture":"#0","tintindex":0},"up":{"uv":[13.0,1.0,14.0,2.0],"rotation":0,"texture":"#0","tintindex":0},"west":{"uv":[13.0,1.0,14.0,2.0],"rotation":180,"texture":"#0","tintindex":0}}}],"display":{"head":{"translation":[0.0,-6.4,0.0],"rotation":[0.0,0.0,0.0],"scale":[3.8095,3.8095,3.8095]}}}