{
    "parent": "item/generated",
    "textures": {
        "layer0": "item/pufferfish"
    },
    "overrides": [
      
      {"predicate": {"custom_model_data":1}, "model": "man10/fish/subesubemanjuugani"},
      {"predicate": {"custom_model_data":2}, "model": "man10/fish/akakurage"},
      {"predicate": {"custom_model_data":3}, "model": "man10/fish/umihebi"},
      {"predicate": {"custom_model_data":4}, "model": "man10/fish/dwarf_pufferfish"},

      {"predicate": {"custom_model_data":5}, "model": "item/pufferfish"}
    ]
}
